mf6Voronoi/__init__.py
mf6Voronoi/geoUtils.py
mf6Voronoi/geoVoronoi.py
mf6Voronoi/meshProperties.py
mf6Voronoi/utils.py
mf6Voronoi/examples/json/templates.json
mf6Voronoi/examples/notebooks/p1_generateVoronoi.ipynb
mf6Voronoi/examples/notebooks/p2_modelCreation.ipynb
mf6Voronoi/examples/notebooks/p3_obsCalculated.ipynb
mf6Voronoi/examples/notebooks/p4_vtkGeneration.ipynb
mf6Voronoi/examples/notebooks/p5_multilayeredTransient.ipynb
mf6Voronoi/examples/notebooks/p6_basicTransport.ipynb
mf6Voronoi/examples/notebooks/p7_seawaterIntrusion.ipynb
mf6Voronoi/tools/__init__.py
mf6Voronoi/tools/cellWork.py
mf6Voronoi/tools/graphs2d.py
mf6Voronoi/tools/vtkGen.py
mf6voronoi-0.0.37.dist-info/licenses/LICENSE
mf6voronoi-0.0.37.dist-info/METADATA
mf6voronoi-0.0.37.dist-info/WHEEL
mf6voronoi-0.0.37.dist-info/top_level.txt
mf6voronoi-0.0.37.dist-info/RECORD
